orama_cache/__init__.py
orama_cache/cache.py
orama_cache/constants.py
orama_cache/memcached_stats.py
orama_cache-1.0.3.dist-info/METADATA
orama_cache-1.0.3.dist-info/RECORD
orama_cache-1.0.3.dist-info/WHEEL
orama_cache-1.0.3.dist-info/top_level.txt
